librdflib/__init__.py
librdflib-0.0.1.dist-info/LICENSE
librdflib-0.0.1.dist-info/METADATA
librdflib-0.0.1.dist-info/WHEEL
librdflib-0.0.1.dist-info/entry_points.txt
librdflib-0.0.1.dist-info/top_level.txt
librdflib-0.0.1.dist-info/RECORD
