Metadata-Version: 2.1
Name: librdflib
Version: 0.0.1
Summary: librdf parser for rdflib
Home-page: https://github.com/tgbugs/pyontutils/tree/master/librdflib
Author: Tom Gillespie
Author-email: tgbugs@gmail.com
License: MIT
Keywords: rdflib librdf rdf parser parsing ttl rdfxml
Platform: UNKNOWN
Classifier: Development Status :: 3 - Alpha
Classifier: License :: OSI Approved :: MIT License
Classifier: Programming Language :: Python :: 3
Requires-Python: >=3
Requires-Dist: rdflib
Provides-Extra: dev
Provides-Extra: test
Requires-Dist: pytest ; extra == 'test'
Requires-Dist: pytest-runner ; extra == 'test'
